awslabs/__init__.py
awslabs/stepfunctions_tool_mcp_server/__init__.py
awslabs/stepfunctions_tool_mcp_server/aws_helper.py
awslabs/stepfunctions_tool_mcp_server/server.py
awslabs_stepfunctions_tool_mcp_server-0.1.17.dist-info/METADATA
awslabs_stepfunctions_tool_mcp_server-0.1.17.dist-info/WHEEL
awslabs_stepfunctions_tool_mcp_server-0.1.17.dist-info/entry_points.txt
awslabs_stepfunctions_tool_mcp_server-0.1.17.dist-info/licenses/LICENSE
awslabs_stepfunctions_tool_mcp_server-0.1.17.dist-info/licenses/NOTICE
awslabs_stepfunctions_tool_mcp_server-0.1.17.dist-info/RECORD
